cron4py/__init__.py
cron4py/cron.py
cron4py/funcs.py
cron4py-1.0.2.dist-info/METADATA
cron4py-1.0.2.dist-info/WHEEL
cron4py-1.0.2.dist-info/top_level.txt
cron4py-1.0.2.dist-info/RECORD
