Metadata-Version: 2.1
Name: cron4py
Version: 1.0.2
Summary: Cron to list datetime
Home-page: UNKNOWN
Author-email: kivdev@yandex.ru
License: UNKNOWN
Platform: UNKNOWN
